{
  "name": "blackbird",
  "type": "dark",
  "colors": {
    "editorPane.background": "#3EC841",
    "editor.background": "#000000",
    "editor.foreground": "#fdf7cd",
    "foreground": "#fdf7cd",
    "sideBar.background": "#000000",
    "titleBar.activeBackground": "#000000",
    "titleBar.inactiveBackground": "#000000",
    "titleBar.border": "#222029",
    "sideBarTitle.foreground": "#3EC841",
    "tab.inactiveBackground": "#000000",
    "tab.activeForeground": "#fdf7cd",
    "tab.inactiveForeground": "#fdf7cd",
    "statusBar.foreground": "#fdf7cd",
    "tab.activeBorderTop": "#3EC841",
    "tab.activeModifiedBorder": "#E1DB3F",
    "tab.activeBackground": "#000000",
    "titleBar.activeForeground": "#3EC841",
    "editorGroupHeader.tabsBackground": "#000000",
    "button.background": "#000000",
    "button.foreground": "#3EC841",
    "button.hoverBackground": "#000000",
    "statusBar.border": "#222029",
    "statusBar.background": "#000000",
    "statusBar.noFolderBackground": "#000000",
    "statusBar.debuggingBackground": "#E1DB3F",
    "notificationCenterHeader.background": "#000000",
    "notificationCenter.border": "#222029",
    "notificationToast.border": "#222029",
    "notifications.background": "#000000",
    "notifications.border": "#222029",
    "notificationsInfoIcon.foreground": "#3EC841",
    "notificationsWarningIcon.foreground": "#E1DB3F",
    "notificationsErrorIcon.foreground": "#e92741",
    "tab.border": "#222029",
    "editorGroupHeader.tabsBorder": "#222029",
    "badge.background": "#222029",
    "sideBarSectionHeader.background": "#000000",
    "sideBarSectionHeader.foreground": "#3EC841",
    "sideBarSectionHeader.border": "#222029",
    "sideBar.dropBackground": "#3EC841",
    "sideBar.border": "#222029",
    "progressBar.background": "#3EC841",
    "gitDecoration.addedResourceForeground": "#3EC841",
    "gitDecoration.deletedResourceForeground": "#e92741",
    "gitDecoration.modifiedResourceForeground": "#E1DB3F",
    "gitDecoration.untrackedResourceForeground": "#3EC841",
    "gitDecoration.stageModifiedResourceForeground": "#E1DB3F",
    "list.errorForeground": "#e92741",
    "contrastBorder": "#222029",
    "input.background": "#000000",
    "input.border": "#222029",
    "inputOption.activeBorder": "#3EC841",
    "welcomePage.background": "#000000",
    "minimapGutter.addedBackground": "#3EC841",
    "minimapGutter.deletedBackground": "#e92741",
    "minimapGutter.modifiedBackground": "#E1DB3F",
    "minimap.selectionHighlight": "#222029",
    "minimap.errorHighlight": "#e92741",
    "minimap.warningHighlight": "#E1DB3F",
    "editorGutter.addedBackground": "#3EC841",
    "editorGutter.deletedBackground": "#e92741",
    "editorGutter.modifiedBackground": "#E1DB3F",
    "quickInput.background": "#000000",
    "icon.foreground": "#fdf7cd",
    "list.highlightForeground": "#e92741",
    "list.focusBackground": "#222029",
    "editorError.foreground": "#e92741",
    "errorLens.errorForeground": "#e92741",
    "editorWarning.foreground": "#E1DB3F",
    "errorLens.warningForeground": "#E1DB3F",
    "editorInfo.foreground": "#418EDD",
    "errorLens.infoForeground": "#418EDD",
    "editorCursor.foreground": "#ffffff",
    "editorLineNumber.foreground": "#343c50",
    "editorLineNumber.activeForeground": "#fdf7cd",
    "editorIndentGuide.background": "#222029",
    "editorIndentGuide.activeBackground": "#343c50",
    "editorRuler.foreground": "#222029",
    "focusBorder": "#222029",
    "checkbox.background": "#000000",
    "dropdown.background": "#000000",
    "dropdown.border": "#222029",
    "editorWidget.background": "#000000",
    "editorWidget.border": "#222029",
    "editorSuggestWidget.background": "#000000",
    "editorSuggestWidget.border": "#222029",
    "editorSuggestWidget.selectedBackground": "#222029",
    "titleBar.inactiveForeground": "#fdf7cd",
    "list.hoverBackground": "#222029",
    "list.activeSelectionBackground": "#222029",
    "list.inactiveSelectionBackground": "#000000",
    "settings.modifiedItemIndicator": "#e92741",
    "activityBar.background": "#000000",
    "activityBar.activeBorder": "#e92741",
    "activityBarBadge.background": "#222029",
    "editor.selectionBackground": "#222029",
    "statusBar.debuggingForeground": "#000000",
    "debugToolBar.background": "#000000",
    "debugToolBar.border": "#222029",
    "settings.textInputBorder": "#222029",
    "textLink.activeForeground": "#e92741",
    "textLink.foreground": "#e92741",
    "debugIcon.pauseForeground": "#418EDD",
    "debugIcon.restartForeground": "#3EC841",
    "debugIcon.stopForeground": "#e92741",
    "list.dropBackground": "#222029",
    "editorGroup.dropBackground": "#e92741",
    "tree.indentGuidesStroke": "#fdf7cd",
    "editor.snippetTabstopHighlightBackground": "#000000",
    "editor.snippetTabstopHighlightBorder": "#222029",
    "terminalCursor.foreground": "#ffffff",
    "terminal.selectionBackground": "#222029",
    "terminal.foreground": "#fdf7cd",
    "terminal.ansiBrightGreen": "#3EC841",
    "terminal.ansiBrightCyan": "#00ecd8",
    "terminal.ansiBrightBlue": "#418EDD",
    "terminal.ansiBrightWhite": "#fdf7cd",
    "terminal.ansiBrightBlack": "#222029",
    "terminal.ansiBrightRed": "#e92741",
    "terminal.ansiBrightYellow": "#E1DB3F",
    "terminal.ansiBrightMagenta": "#ff00cc",
    "terminal.ansiGreen": "#3EC841",
    "terminal.ansiCyan": "#00ecd8",
    "terminal.ansiBlue": "#418EDD",
    "terminal.ansiWhite": "#fdf7cd",
    "terminal.ansiBlack": "#222029",
    "terminal.ansiRed": "#e92741",
    "terminal.ansiYellow": "#E1DB3F",
    "terminal.ansiMagenta": "#ff00cc",
    "panelTitle.activeForeground": "#fdf7cd",
    "panel.border": "#222029",
    "panelSectionHeader.border": "#222029",
    "panelSection.border": "#222029",
    "terminal.border": "#222029",
    "editorGroup.border": "#222029",
    "dropdown.foreground": "#fdf7cd",
    "rust_analyzer.inlayHints.foreground": "#5597a3"
  },
  "tokenColors": [
    {
      "name": "Red Italic",
      "scope": [
        "keyword",
        "meta.selector.css",
        "keyword.control.at-rule.media.css",
        "storage.modifier",
        "keyword.control.export",
        "variable.language.this"
      ],
      "settings": {
        "foreground": "#e92741",
        "fontStyle": "italic"
      }
    },
    {
      "name": "White",
      "scope": [
        "entity.other.attribute-name",
        "support.type.property-name.css",
        "support.class.latex"
      ],
      "settings": {
        "foreground": "#fdf7cd",
        "fontStyle": ""
      }
    },
    {
      "name": "Red Bold",
      "scope": [
        "entity.name.tag",
        "markup.heading",
        "support.type.property-name",
        "variable.other.property"
      ],
      "settings": {
        "foreground": "#e92741",
        "fontStyle": "bold"
      }
    },
    {
      "name": "Red",
      "scope": [
        "keyword.operator",
        "meta.property-value.css",
        "keyword.other.special-method",
        "keyword.key",
        "constant.other.math.tex",
        "constant.character.math.tex"
      ],
      "settings": {
        "foreground": "#e92741",
        "fontStyle": ""
      }
    },
    {
      "name": "Light Gray",
      "scope": ["variable.other.property", "meta.attribute"],
      "settings": {
        "foreground": "#5597a3",
        "fontStyle": ""
      }
    },
    {
      "name": "Yellow",
      "scope": ["string", "punctuation.definition.string"],
      "settings": {
        "foreground": "#E1DB3F",
        "fontStyle": ""
      }
    },
    {
      "name": "Blue",
      "scope": [
        "constant.numeric",
        "support.class.math",
        "constant.character.math",
        "entity.other.keyframe-offset.percentage.css",
        "punctuation.math.begin.bracket.curly",
        "punctuation.math.end.bracket.curly",
        "punctuation.math.operator.latex"
      ],
      "settings": {
        "foreground": "#418EDD",
        "fontStyle": ""
      }
    },
    {
      "name": "Blue Italic",
      "scope": ["support.class.math", "constant.character.math"],
      "settings": {
        "foreground": "#418EDD",
        "fontStyle": "italic"
      }
    },
    {
      "name": "Green",
      "scope": [
        "entity.name.function",
        "support.function",
        "meta.function-call.generic",
        "entity.other.attribute-name.pseudo-element.css",
        "support.class",
        "entity.other.attribute-name.table.toml",
        "constant.other.general.math.tex"
      ],
      "settings": {
        "foreground": "#3EC841",
        "fontStyle": ""
      }
    },
    {
      "name": "Green Bold",
      "scope": ["entity.other.attribute-name.table.toml"],
      "settings": {
        "foreground": "#3EC841",
        "fontStyle": "bold"
      }
    },
    {
      "name": "Orange",
      "scope": [
        "meta.template.expression",
        "meta.return-type",
        "support.type.primitive",
        "entity.name.type"
      ],
      "settings": {
        "foreground": "#ff9900"
      }
    },
    {
      "name": "Gray",
      "scope": ["comment"],
      "settings": {
        "foreground": "#343c50",
        "fontStyle": ""
      }
    },
    {
      "name": "Teal Italic",
      "scope": [
        "storage",
        "entity.other.attribute-name.json",
        "constant",
        "keyword.control.default",
        "variable.parameter.function.latex",
        "entity.other.attribute-name.pseudo-element.css",
        "meta.separator"
      ],
      "settings": {
        "foreground": "#00ecd8",
        "fontStyle": "italic"
      }
    },
    {
      "name": "Teal",
      "scope": ["constant.character.escape"],
      "settings": {
        "foreground": "#00ecd8",
        "fontStyle": ""
      }
    }
  ]
}
